light_scores/__init__.py
light_scores/light_scores.py
light_scores/normalize.py
light_scores-0.1.2.dist-info/WHEEL
light_scores-0.1.2.dist-info/METADATA
light_scores-0.1.2.dist-info/RECORD
