Metadata-Version: 2.1
Name: light-scores
Version: 0.1.2
Summary: 
Home-page: https://github.com/ffreemt/light-scores
License: MIT
Author: freemt
Requires-Python: >=3.7,<4.0
Classifier: License :: OSI Approved :: MIT License
Classifier: Programming Language :: Python :: 3
Classifier: Programming Language :: Python :: 3.7
Classifier: Programming Language :: Python :: 3.8
Classifier: Programming Language :: Python :: 3.9
Requires-Dist: loguru (>=0.5.3,<0.6.0)
Requires-Dist: logzero (>=1.7.0,<2.0.0)
Requires-Dist: nltk (>=3.6.2,<4.0.0)
Requires-Dist: rank-bm25 (>=0.2.1,<0.3.0)
Project-URL: Repository, https://github.com/ffreemt/light-scores
